ocspbot/__init__.py
ocspbot/__main__.py
ocspbot-0.9.3.dist-info/LICENSE.txt
ocspbot-0.9.3.dist-info/METADATA
ocspbot-0.9.3.dist-info/RECORD
ocspbot-0.9.3.dist-info/WHEEL
ocspbot-0.9.3.dist-info/entry_points.txt
ocspbot-0.9.3.dist-info/top_level.txt
