Metadata-Version: 2.1
Name: ocspbot
Version: 0.9.3
Summary: Ensure up-to-date OCSP responses for certificates are available.
Home-page: https://github.com/felixfontein/ocspbot
Author: Felix Fontein
Author-email: felix@fontein.de
License: MIT
Keywords: ocsp response update
Platform: UNKNOWN
Classifier: Development Status :: 4 - Beta
Classifier: Intended Audience :: System Administrators
Classifier: Topic :: Internet :: WWW/HTTP :: Site Management
Classifier: Topic :: Security
Classifier: Topic :: Utilities
Classifier: License :: OSI Approved :: MIT License
Classifier: Programming Language :: Python :: 2
Classifier: Programming Language :: Python :: 2.7
Classifier: Programming Language :: Python :: 3
Classifier: Programming Language :: Python :: 3.3
Classifier: Programming Language :: Python :: 3.4
Classifier: Programming Language :: Python :: 3.5
Classifier: Programming Language :: Python :: 3.6
Classifier: Programming Language :: Python :: 3.7
Requires-Dist: setuptools (>=20.3)
Requires-Dist: pyyaml
